{
    "amoghg75@yahoo.com": {
        "accent": "darkorange2",
        "font": "Georgia",
        "lightBG": "1",
        "darkBG": "2"
    },
    "tickd@gmail.com": {
        "accent": "dodgerblue2",
        "font": "Bahnschrift"
    },
    "omar@gmail.com": {
        "accent": "crimson",
        "font": "Bahnschrift"
    },
    "ajayng@tickd.co.uk": {
        "accent": "dodgerblue2",
        "font": "Bahnschrift"
    },
    "test@gmail.com": {
        "accent": "dodgerblue2",
        "font": "Bahnschrift"
    },
    "snehan@gmail.com": {
        "accent": "dodgerblue2",
        "font": "Bahnschrift"
    },
    "freitasarod@gmail.com": {
        "accent": "dodgerblue2",
        "font": "Bahnschrift"
    },
    "sufyaan.hussain@outlook.com": {
        "accent": "dodgerblue2",
        "font": "Bahnschrift"
    },
    "tickd2@gmail.com": {
        "accent": "dodgerblue2",
        "font": "Bahnschrift"
    },
    "bertwaldron@gmail.com": {
        "accent": "dodgerblue2",
        "font": "Bahnschrift"
    },
    "bingbong@gmail.com": {
        "accent": "dodgerblue2",
        "font": "Bahnschrift"
    },
    "tickd.todolist@gmail.com": {
        "accent": "crimson",
        "font": "Bahnschrift"
    },
    "ajayng5678@gmail.com": {
        "accent": "dodgerblue2",
        "font": "Bahnschrift"
    },
    "snehan.biswas2007@gmail.com": {
        "accent": "dodgerblue2",
        "font": "Bahnschrift"
    },
    "test@tickd.com": {
        "accent": "dodgerblue2",
        "font": "Bahnschrift"
    },
    "test4@gmail.com": {
        "accent": "dodgerblue2",
        "font": "Bahnschrift"
    },
    "amogh12711@gmail.com": {
        "accent": "dodgerblue2",
        "font": "Bahnschrift"
    },
    "mytest@testmail.com": {
        "accent": "dodgerblue2",
        "font": "Bahnschrift"
    }
}