{
    "listID": "f1DClQ",
    "shared": [
        "amoghg75@yahoo.com",
        "test123@gmail.com"
    ],
    "tasks": {
        "zLPTTF": {
            "title": "Get groceries",
            "date": "27/2/2025",
            "taskID": "zLPTTF",
            "completed": "False",
            "time": "",
            "priority": "",
            "description": "",
            "listName": "Shopping",
            "starred": "False"
        },
        "fAQpaJ": {
            "title": "Get bananas",
            "date": "26/02/2025",
            "taskID": "fAQpaJ",
            "completed": "False",
            "time": "",
            "priority": "",
            "description": "",
            "listName": "Shopping",
            "starred": "False"
        }
    },
    "completed": {
        "ZNjKHW": {
            "title": "apples",
            "date": "",
            "taskID": "ZNjKHW",
            "completed": "True",
            "time": "",
            "priority": "",
            "description": "",
            "listName": "Shopping"
        },
        "edzHdu": {
            "title": "bananes",
            "date": "15/1/2025",
            "taskID": "edzHdu",
            "completed": "True",
            "time": "10:25",
            "priority": "",
            "description": "Just get the freshest ones, preferably from Ecuador.",
            "listName": "Shopping"
        },
        "JebmNt": {
            "title": "AR MANIIIIII",
            "date": "20/2/2025",
            "taskID": "JebmNt",
            "completed": "True",
            "time": "",
            "priority": "",
            "description": "",
            "listName": "Shopping"
        },
        "NuQbYM": {
            "title": "Trousers varungal AR MANIIII",
            "date": "20/2/2025",
            "taskID": "NuQbYM",
            "completed": "True",
            "time": "",
            "priority": "",
            "description": "",
            "listName": "Shopping"
        },
        "TGjdzQ": {
            "title": "Stir fry ingredients",
            "date": "26/01/2025",
            "taskID": "TGjdzQ",
            "completed": "True",
            "time": "",
            "priority": "",
            "description": "",
            "listName": "Shopping",
            "starred": "False"
        },
        "KyTurX": {
            "title": "Apples",
            "date": "26/01/2025",
            "taskID": "KyTurX",
            "completed": "True",
            "time": "",
            "priority": "",
            "description": "",
            "listName": "Shopping",
            "starred": "False"
        },
        "yMvIku": {
            "title": "Tomatoes",
            "date": "26/01/2025",
            "taskID": "yMvIku",
            "completed": "True",
            "time": "",
            "priority": "",
            "description": "",
            "listName": "Shopping",
            "starred": "False"
        },
        "GIkpoi": {
            "title": "Bananas",
            "date": "26/01/2025",
            "taskID": "GIkpoi",
            "completed": "True",
            "time": "",
            "priority": "",
            "description": "",
            "listName": "Shopping",
            "starred": "False"
        },
        "KtyFvd": {
            "title": "bananas",
            "date": "04/02/2025",
            "taskID": "KtyFvd",
            "completed": "True",
            "time": "",
            "priority": "",
            "description": "",
            "listName": "Shopping",
            "starred": "False"
        }
    },
    "requestsSent": []
}